uniparser_erzya/__init__.py
uniparser_erzya/data_nodiacritics/__init__.py
uniparser_erzya/data_nodiacritics/bad_analyses.txt
uniparser_erzya/data_nodiacritics/lex_rules.txt
uniparser_erzya/data_nodiacritics/lexemes.txt
uniparser_erzya/data_nodiacritics/paradigms.txt
uniparser_erzya/data_strict/__init__.py
uniparser_erzya/data_strict/bad_analyses.txt
uniparser_erzya/data_strict/lex_rules.txt
uniparser_erzya/data_strict/lexemes.txt
uniparser_erzya/data_strict/paradigms.txt
uniparser_erzya-1.1.3.dist-info/LICENSE
uniparser_erzya-1.1.3.dist-info/METADATA
uniparser_erzya-1.1.3.dist-info/WHEEL
uniparser_erzya-1.1.3.dist-info/top_level.txt
uniparser_erzya-1.1.3.dist-info/RECORD
